caolib/__init__.py
caolib/color_text.py
caolib-0.1.9.dist-info/LICENSE
caolib-0.1.9.dist-info/METADATA
caolib-0.1.9.dist-info/WHEEL
caolib-0.1.9.dist-info/top_level.txt
caolib-0.1.9.dist-info/RECORD
